[
    {
      "id": "amoalsenor",
      "titulo": "Amo al Señor",
      "salmo": "Salmo 114",
      "letra": "amo al señor porque escucha...",
      "archivo": "/cantos/resucito/amoalsenor.html"
    },
    {
      "id": "alavíctimapascual",
      "titulo": "A la victima pascual",
      "salmo": "Secuencia de Pascua - Himno lat. «Vlctlmae paschall laudes»",
      "letra": "a la víctima pascual, ofrecemos hoy el sacrificio de alabanza. el cordero ha redimido el rebaño, el inocente ha reconciliado los pecadores al padre. muerte y vida se han enfrentado en un prodigioso duelo: el señor de la vida estaba muerto, mas ahora está vivo y triunfa. dinos tú, maría: ¿qué has visto en el camino?, «la tumba de cristo vacía, la gloria del señor y vivo cristo, los ángeles, las vendas y el sudario». porque cristo, mi esperanza, ¡ha resucitado! y nos precede en galilea, y nos precede en galilea. sí que es cierto, cristo ha resucitado. sí que es cierto, cristo ha resucitado. y nos precede en galilea, y nos precede en galilea. tú, rey victorioso, danos tú la salvación",
      "archivo": "/cantos/resucito/alavíctimapascual.html"
    }
  ]